Metadata-Version: 2.1
Name: nxstart
Version: 1.1.3
Summary: Nintendo Switch homebrew project generator
Home-page: https://github.com/roedesh/nxstart
Author: Ruud Schroën
Author-email: UNKNOWN
License: MIT
Keywords: nintendo switch libnx nx homebrew project generator
Platform: UNKNOWN
Classifier: Development Status :: 5 - Production/Stable
Classifier: Environment :: Console
Classifier: Intended Audience :: Developers
Classifier: License :: OSI Approved :: MIT License
Classifier: Natural Language :: English
Classifier: Programming Language :: Python :: 3.4
Classifier: Programming Language :: Python :: 3.5
Classifier: Programming Language :: Python :: 3.6
Classifier: Topic :: Software Development :: Code Generators
Classifier: Topic :: Utilities
Requires-Dist: Click
